literalenv/__init__.py
literalenv/__main__.py
literalenv-0.1.2.dist-info/WHEEL
literalenv-0.1.2.dist-info/METADATA
literalenv-0.1.2.dist-info/RECORD
