Metadata-Version: 2.1
Name: literalenv
Version: 0.1.2
Summary: Parses an environment variable as a Python literal and outputs it to stdout.
License: MIT
Author: Ellis Percival
Author-email: literalenv@failcode.co.uk
Requires-Python: >=3.6,<4.0
Classifier: License :: OSI Approved :: MIT License
Classifier: Programming Language :: Python :: 3
Classifier: Programming Language :: Python :: 3.6
Classifier: Programming Language :: Python :: 3.7
Classifier: Programming Language :: Python :: 3.8
Classifier: Programming Language :: Python :: 3.9
